cross_monitor_bot/__init__.py
cross_monitor_bot/app.py
cross_monitor_bot/config.py
cross_monitor_bot/run.py
cross_monitor_bot/messagers/__init__.py
cross_monitor_bot/messagers/abc.py
cross_monitor_bot/messagers/tg.py
cross_monitor_bot/methods/__init__.py
cross_monitor_bot/methods/abc.py
cross_monitor_bot/methods/get.py
cross_monitor_bot/methods/ping.py
cross_monitor_bot-0.1.0.dev1.dist-info/LICENSE
cross_monitor_bot-0.1.0.dev1.dist-info/METADATA
cross_monitor_bot-0.1.0.dev1.dist-info/WHEEL
cross_monitor_bot-0.1.0.dev1.dist-info/top_level.txt
cross_monitor_bot-0.1.0.dev1.dist-info/RECORD
